{
    "name":"code1",
    "languages":
    [
        {
            "language":"cs",
            "files":[
                {
                    "name":"Connection",
                    "path":"/Connection.cs"
                },
                {
                    "name":"Node",
                    "path":"/Node.cs"
                }
            ]
        },
        {
            "language":"java",
            "files":[
                {
                    "name":"Connection",
                    "path":"/Connection.java"
                },
                {
                    "name":"Node",
                    "path":"/Node.java"
                }
            ]
        },
        {
            "language":"javascript",
            "files":[
                {
                    "name":"Connection",
                    "path":"/Connection.js"
                },
                {
                    "name":"Node",
                    "path":"/Node.js"
                }
            ]
        },
        {
            "language":"python",
            "files":[
                {
                    "name":"Connection",
                    "path":"/Connection.py"
                },
                {
                    "name":"Node",
                    "path":"/Node.py"
                }
            ]
        }
    ]
}